  {
    "id": "PSY_magi_magic_revolver_ver6",
    "copy-from": "pistol_revolver",
    "looks_like": "sw_619",
    "type": "GUN",
    "name": "마나 카트리지 전용 권총 세쿠스[MWMI]",
    "extend": { "flags": [ "MAGIC_FOCUS" ] },
    "description": "마법사를 위해 설계된 마나 카트리지 탄 전용 권총 세쿠스입니다. 숙련된 마법사밖에 다룰 수 없는 총으로, 그 위력은 보증 되있습니다.",
    "weight": "1200 g",
    "volume": "1 L",
    "price": 60000,
    "to_hit": -3,
    "bashing": 12,
    "material": [ "steel", "wood","copper","silver","gold","platinum" ],
    "symbol": "(",
    "color": "dark_gray",
    "ammo": "PSY_magi_44_magic",
    "ranged_damage": { "damage_type": "bullet", "amount": 2 },
    "dispersion": 620,
    "durability": 7,
    "loudness": 25,
    "pocket_data": [ 
      { "pocket_type": "MAGAZINE",
        "holster": true, 
        "rigid": true, 
        "ammo_restriction": { "PSY_magi_44_magic": 6 },
        "allowed_speedloaders": [ "PSY_magi_44_magic_speedloader6" ]
      }
    ],
    "valid_mod_locations": [
      [ "accessories", 2 ],
      [ "barrel", 1 ],
      [ "bore", 1 ],
      [ "grip", 1 ],
      [ "mechanism", 4 ],
      [ "rail", 1 ],
      [ "sights", 1 ],
      [ "stock", 1 ],
      [ "underbarrel", 1 ]
    ]
  }