[
	{
		"id":"card_call_crate_ev1_1",
		"type":"TOOL",
		"looks_like":"card_call_crate_1",
		"name":"크리스마스 가챠 티켓",
		"description":"기묘한 도안이나 문양이 그려진 티켓. 한 장을 뜯어서 의사를 담으면 무슨 일이 일어날지도 모릅니다.반경 3미터 이내에 아무것도 없는 상태로 사용해 주세요.이것을 만들기 위해서는 먼저 '산타로스의 메모'를 구해야 합니다.",
		"weight":"1 g",
		"volume":"1 ml",
		"material":[ "paper" ],
		"symbol":"_",
		"color":"light_gray",
		"flags":[ "TRADER_AVOID","NO_UNLOAD","NO_RELOAD","UNBREAKABLE_MELEE" ],
		"pocket_data":[ { "pocket_type": "MAGAZINE",  "ammo_restriction": { "ncard_misc_t": 1 } } ],
		"use_action":{ "type": "cast_spell", "spell_id": "call_crate_ev1_", "no_fail": true, "level": 0 },
		"to_hit":-1,
		"initial_charges":1,
		"max_charges":1,
		"charges_per_use":1
	}
,
	{
		"id":"card_call_crate_ev1_2",
		"type":"TOOL",
		"looks_like":"card_call_crate_1",
		"name":"크리스마스 가챠 티켓 (10개 묶음)",
		"description":"기묘한 도안이나 문양이 그려진 티켓. 한 장을 뜯어서 의사를 담으면 무슨 일이 일어날지도 모릅니다.반경 3미터 이내에 아무것도 없는 상태로 사용해 주세요.이것을 만들기 위해서는 먼저 '산타로스의 메모'를 구해야 합니다.",
		"weight":"1 g",
		"volume":"1 ml",
		"material":[ "paper" ],
		"symbol":"_",
		"color":"light_gray",
		"flags":[ "TRADER_AVOID","NO_UNLOAD","NO_RELOAD","UNBREAKABLE_MELEE" ],
		"pocket_data":[ { "pocket_type": "MAGAZINE",  "ammo_restriction": { "ncard_misc_t": 10 } } ],
		"use_action":{ "type": "cast_spell", "spell_id": "call_crate_ev1_", "no_fail": true, "level": 0 },
		"to_hit":-1,
		"initial_charges":10,
		"max_charges":10,
		"charges_per_use":1
	}
,
	{
		"id":"card_call_crate_ev1_3",
		"type":"TOOL",
		"looks_like":"card_call_crate_1",
		"name":"크리스마스 가챠 티켓 (100개 묶음)",
		"description":"기묘한 도안이나 문양이 그려진 티켓. 한 장을 뜯어서 의사를 담으면 무슨 일이 일어날지도 모릅니다.반경 3미터 이내에 아무것도 없는 상태로 사용해 주세요.이것을 만들기 위해서는 먼저 '산타로스의 메모'를 구해야 합니다.",
		"weight":"1 g",
		"volume":"1 ml",
		"material":[ "paper" ],
		"symbol":"_",
		"color":"light_gray",
		"flags":[ "TRADER_AVOID","NO_UNLOAD","NO_RELOAD","UNBREAKABLE_MELEE" ],
		"pocket_data":[ { "pocket_type": "MAGAZINE",  "ammo_restriction": { "ncard_misc_t": 100 } } ],
		"use_action":{ "type": "cast_spell", "spell_id": "call_crate_ev1_", "no_fail": true, "level": 0 },
		"to_hit":-1,
		"initial_charges":100,
		"max_charges":100,
		"charges_per_use":1
	}
,
	{
		"id":"ncard_misc_ev1_keystone",
		"type":"BOOK",
		"looks_like":"card_call_crate_1",
		"name":"산타클로스의 메모",
		"description":"이것을 읽음으로써 크리스마스 가챠 티켓을 작성하는 방법을 알 수 있습니다.",
		"weight":"30 g",
		"volume":"30 ml",
		"material":[ "paper" ],
		"symbol":"_",
		"color":"white",
		"flags":[ "TRADER_AVOID","UNBREAKABLE_MELEE" ],
		"skill":"fabrication",
		"max_level":1,
		"intelligence":1,
		"time":20,
		"fun":1
	}
,
	{
		"id":"ncard_misc_ev1_xmas_box",
		"type":"TOOL",
		"category":"tools",
		"looks_like":"card_call_crate_1",
		"name":"선물상자",
		"description":"알록달록한 색상의 포장지에 싸인 상자입니다.좋은 게 들어있을 수도 있어요.사용하는 커맨드(a키)로 설치할 수 있습니다.",
		"weight":"30 g",
		"volume":"30 ml",
		"material":[ "ncard_material_dimensionsteel" ],
		"symbol":"n",
		"color":"green",
		"flags":[ "TRADER_AVOID","UNBREAKABLE_MELEE" ],
		"use_action":{ "type": "deploy_furn", "furn_type": "f_lootcrate_ev1_xmas_box" }
	}
,
	{
		"id":"card_call_crate_ev2_1",
		"type":"TOOL",
		"looks_like":"card_call_crate_1",
		"name":"NEW YEAR 가챠 티켓",
		"description":"기묘한 도안이나 문양이 그려진 티켓. 한 장을 뜯어서 의사를 담으면 무슨 일이 일어날지도 모릅니다.반경 3미터 이내에 아무것도 없는 상태로 사용해 주세요.이것을 만들려면 먼저 '십이지상극도'를 손에 넣어야 합니다.",
		"weight":"1 g",
		"volume":"1 ml",
		"material":[ "paper" ],
		"symbol":"_",
		"color":"light_gray",
		"flags":[ "TRADER_AVOID","NO_UNLOAD","NO_RELOAD","UNBREAKABLE_MELEE" ],
		"pocket_data":[ { "pocket_type": "MAGAZINE",  "ammo_restriction": { "ncard_misc_t": 1 } } ],
		"use_action":{ "type": "cast_spell", "spell_id": "call_crate_ev2_", "no_fail": true, "level": 0 },
		"to_hit":-1,
		"initial_charges":1,
		"max_charges":1,
		"charges_per_use":1
	}
,
	{
		"id":"card_call_crate_ev2_2",
		"type":"TOOL",
		"looks_like":"card_call_crate_1",
		"name":"NEW YEAR 가챠 티켓 (10개 묶음)",
		"description":"기묘한 도안이나 문양이 그려진 티켓. 한 장을 뜯어서 의사를 담으면 무슨 일이 일어날지도 모릅니다.반경 3미터 이내에 아무것도 없는 상태로 사용해 주세요.이것을 만들려면 먼저 '십이지상극도'를 손에 넣어야 합니다",
		"weight":"1 g",
		"volume":"1 ml",
		"material":[ "paper" ],
		"symbol":"_",
		"color":"light_gray",
		"flags":[ "TRADER_AVOID","NO_UNLOAD","NO_RELOAD","UNBREAKABLE_MELEE" ],
		"pocket_data":[ { "pocket_type": "MAGAZINE",  "ammo_restriction": { "ncard_misc_t": 10 } } ],
		"use_action":{ "type": "cast_spell", "spell_id": "call_crate_ev2_", "no_fail": true, "level": 0 },
		"to_hit":-1,
		"initial_charges":10,
		"max_charges":10,
		"charges_per_use":1
	}
,
	{
		"id":"card_call_crate_ev2_3",
		"type":"TOOL",
		"looks_like":"card_call_crate_1",
		"name":"NEW YEAR 가챠 티켓 (100개 묶음)",
		"description":"기묘한 도안이나 문양이 그려진 티켓. 한 장을 뜯어서 의사를 담으면 무슨 일이 일어날지도 모릅니다.반경 3미터 이내에 아무것도 없는 상태로 사용해 주세요.이것을 만들려면 먼저 '십이지상극도'를 손에 넣어야 합니다",
		"weight":"1 g",
		"volume":"1 ml",
		"material":[ "paper" ],
		"symbol":"_",
		"color":"light_gray",
		"flags":[ "TRADER_AVOID","NO_UNLOAD","NO_RELOAD","UNBREAKABLE_MELEE" ],
		"pocket_data":[ { "pocket_type": "MAGAZINE",  "ammo_restriction": { "ncard_misc_t": 100 } } ],
		"use_action":{ "type": "cast_spell", "spell_id": "call_crate_ev2_", "no_fail": true, "level": 0 },
		"to_hit":-1,
		"initial_charges":100,
		"max_charges":100,
		"charges_per_use":1
	}
,
	{
		"id":"ncard_misc_ev2_keystone",
		"type":"BOOK",
		"looks_like":"ncard_misc_ev1_keystone",
		"name":"십이지상극도",
		"description":"이걸 읽으면 NEW YEAR 가챠 티켓을 만드는 방법을 알게됩니다.",
		"weight":"30 g",
		"volume":"30 ml",
		"material":[ "paper" ],
		"symbol":"_",
		"color":"white",
		"flags":[ "TRADER_AVOID","UNBREAKABLE_MELEE" ],
		"skill":"fabrication",
		"max_level":1,
		"intelligence":1,
		"time":20,
		"fun":1
	}
,
	{
		"id":"ncard_misc_ev2_event_box",
		"type":"TOOL",
		"category":"tools",
		"looks_like":"card_call_crate_1",
		"name":"복주머니",
		"description":"화려한 색상이 눈길을 끄는 빨간 종이봉투입니다.좋은 게 들어있을 수도 있어요.사용하는 커맨드(a키)로 설치할 수 있습니다.",
		"weight":"30 g",
		"volume":"30 ml",
		"material":[ "ncard_material_dimensionsteel" ],
		"symbol":"n",
		"color":"red",
		"flags":[ "TRADER_AVOID","UNBREAKABLE_MELEE" ],
		"use_action":{ "type": "deploy_furn", "furn_type": "f_lootcrate_ev2_event_box" }
	}
,
	{
		"id":"card_call_crate_ev3_1",
		"type":"TOOL",
		"looks_like":"card_call_crate_1",
		"name":"요호마을 가챠 티켓",
		"description":"기묘한 도안이나 문양이 그려진 티켓. 한 장을 뜯어서 의사를 담으면 무슨 일이 일어날지도 모릅니다.반경 3미터 이내에 아무것도 없는 상태로 사용해 주세요.이것을 만들기 위해서는 먼저 '벚꽃의 서'를 구해야 합니다.",
		"weight":"1 g",
		"volume":"1 ml",
		"material":[ "paper" ],
		"symbol":"_",
		"color":"light_gray",
		"flags":[ "TRADER_AVOID","NO_UNLOAD","NO_RELOAD","UNBREAKABLE_MELEE" ],
		"pocket_data":[ { "pocket_type": "MAGAZINE",  "ammo_restriction": { "ncard_misc_t": 1 } } ],
		"use_action":{ "type": "cast_spell", "spell_id": "call_crate_ev3_", "no_fail": true, "level": 0 },
		"to_hit":-1,
		"initial_charges":1,
		"max_charges":1,
		"charges_per_use":1
	}
,
	{
		"id":"card_call_crate_ev3_2",
		"type":"TOOL",
		"looks_like":"card_call_crate_1",
		"name":"요호마을 가챠 티켓 (10개 묶음)",
		"description":"기묘한 도안이나 문양이 그려진 티켓. 한 장을 뜯어서 의사를 담으면 무슨 일이 일어날지도 모릅니다.반경 3미터 이내에 아무것도 없는 상태로 사용해 주세요.이것을 만들기 위해서는 먼저 '벚꽃의 서'를 구해야 합니다.",
		"weight":"1 g",
		"volume":"1 ml",
		"material":[ "paper" ],
		"symbol":"_",
		"color":"light_gray",
		"flags":[ "TRADER_AVOID","NO_UNLOAD","NO_RELOAD","UNBREAKABLE_MELEE" ],
		"pocket_data":[ { "pocket_type": "MAGAZINE",  "ammo_restriction": { "ncard_misc_t": 10 } } ],
		"use_action":{ "type": "cast_spell", "spell_id": "call_crate_ev3_", "no_fail": true, "level": 0 },
		"to_hit":-1,
		"initial_charges":10,
		"max_charges":10,
		"charges_per_use":1
	}
,
	{
		"id":"card_call_crate_ev3_3",
		"type":"TOOL",
		"looks_like":"card_call_crate_1",
		"name":"요호마을 가챠 티켓 (100개 묶음)",
		"description":"기묘한 도안이나 문양이 그려진 티켓. 한 장을 뜯어서 의사를 담으면 무슨 일이 일어날지도 모릅니다.반경 3미터 이내에 아무것도 없는 상태로 사용해 주세요.이것을 만들기 위해서는 먼저 '벚꽃의 서'를 구해야 합니다.",
		"weight":"1 g",
		"volume":"1 ml",
		"material":[ "paper" ],
		"symbol":"_",
		"color":"light_gray",
		"flags":[ "TRADER_AVOID","NO_UNLOAD","NO_RELOAD","UNBREAKABLE_MELEE" ],
		"pocket_data":[ { "pocket_type": "MAGAZINE",  "ammo_restriction": { "ncard_misc_t": 100 } } ],
		"use_action":{ "type": "cast_spell", "spell_id": "call_crate_ev3_", "no_fail": true, "level": 0 },
		"to_hit":-1,
		"initial_charges":100,
		"max_charges":100,
		"charges_per_use":1
	}
,
	{
		"id":"ncard_misc_ev3_keystone",
		"type":"BOOK",
		"looks_like":"ncard_misc_ev1_keystone",
		"name":"벚꽃의 서",
		"description":"이것을 읽으면 요호마을 가챠 티켓의 작성방법을 알게됩니다.",
		"weight":"30 g",
		"volume":"30 ml",
		"material":[ "paper" ],
		"symbol":"_",
		"color":"white",
		"flags":[ "TRADER_AVOID","UNBREAKABLE_MELEE" ],
		"skill":"fabrication",
		"max_level":1,
		"intelligence":1,
		"time":20,
		"fun":1
	}
,
	{
		"id":"ncard_misc_ev3_event_box",
		"type":"TOOL",
		"category":"tools",
		"looks_like":"card_call_crate_1",
		"name":"괴짝",
		"description":"고풍스러운 괴짝입니다.좋은 게 들어있을 수도 있어요.사용하는 커맨드(a키)로 설치할 수 있습니다.",
		"weight":"30 g",
		"volume":"30 ml",
		"material":[ "ncard_material_dimensionsteel" ],
		"symbol":"n",
		"color":"yellow",
		"flags":[ "TRADER_AVOID","UNBREAKABLE_MELEE" ],
		"use_action":{ "type": "deploy_furn", "furn_type": "f_lootcrate_ev3_event_box" }
	}
,
	{
		"id":"card_call_crate_ev5_1",
		"type":"TOOL",
		"looks_like":"card_call_crate_1",
		"name":"안면 가챠 티켓",
		"description":"기묘한 도안이나 문양이 그려진 티켓. 한 장 뜯어서 의사를 담으면 무슨 일이 일어날지도 모릅니다.반경 3미터 이내에 아무것도 없는 상태에서 사용하십시오.이것을 만들려면 먼저 '숙면대전'을 구해야 합니다.",
		"weight":"1 g",
		"volume":"1 ml",
		"material":[ "paper" ],
		"symbol":"_",
		"color":"light_gray",
		"flags":[ "TRADER_AVOID","NO_UNLOAD","NO_RELOAD","UNBREAKABLE_MELEE" ],
		"pocket_data":[ { "pocket_type": "MAGAZINE",  "ammo_restriction": { "ncard_misc_t": 1 } } ],
		"use_action":{ "type": "cast_spell", "spell_id": "call_crate_ev5_", "no_fail": true, "level": 0 },
		"to_hit":-1,
		"initial_charges":1,
		"max_charges":1,
		"charges_per_use":1
	}
,
	{
		"id":"card_call_crate_ev5_2",
		"type":"TOOL",
		"looks_like":"card_call_crate_1",
		"name":"안면 가챠 티켓(10개 묶음)",
		"description":"기묘한 도안이나 문양이 그려진 티켓. 한 장 뜯어서 의사를 담으면 무슨 일이 일어날지도 모릅니다.반경 3미터 이내에 아무것도 없는 상태에서 사용하십시오.이것을 만들려면 먼저 '숙면대전'을 구해야 합니다.",
		"weight":"1 g",
		"volume":"1 ml",
		"material":[ "paper" ],
		"symbol":"_",
		"color":"light_gray",
		"flags":[ "TRADER_AVOID","NO_UNLOAD","NO_RELOAD","UNBREAKABLE_MELEE" ],
		"pocket_data":[ { "pocket_type": "MAGAZINE",  "ammo_restriction": { "ncard_misc_t": 10 } } ],
		"use_action":{ "type": "cast_spell", "spell_id": "call_crate_ev5_", "no_fail": true, "level": 0 },
		"to_hit":-1,
		"initial_charges":10,
		"max_charges":10,
		"charges_per_use":1
	}
,
	{
		"id":"card_call_crate_ev5_3",
		"type":"TOOL",
		"looks_like":"card_call_crate_1",
		"name":"안면 가챠 티켓(100개 묶음)",
		"description":"기묘한 도안이나 문양이 그려진 티켓. 한 장 뜯어서 의사를 담으면 무슨 일이 일어날지도 모릅니다.반경 3미터 이내에 아무것도 없는 상태에서 사용하십시오.이것을 만들려면 먼저 '숙면대전'을 구해야 합니다.",
		"weight":"1 g",
		"volume":"1 ml",
		"material":[ "paper" ],
		"symbol":"_",
		"color":"light_gray",
		"flags":[ "TRADER_AVOID","NO_UNLOAD","NO_RELOAD","UNBREAKABLE_MELEE" ],
		"pocket_data":[ { "pocket_type": "MAGAZINE",  "ammo_restriction": { "ncard_misc_t": 100 } } ],
		"use_action":{ "type": "cast_spell", "spell_id": "call_crate_ev5_", "no_fail": true, "level": 0 },
		"to_hit":-1,
		"initial_charges":100,
		"max_charges":100,
		"charges_per_use":1
	}
,
	{
		"id":"ncard_misc_ev5_keystone",
		"type":"BOOK",
		"looks_like":"ncard_misc_ev1_keystone",
		"name":"숙면대전",
		"description":"이것을 읽는 것으로 안면 뽑기 티켓을 만드는 방법을 알 수 있습니다.",
		"weight":"30 g",
		"volume":"30 ml",
		"material":[ "paper" ],
		"symbol":"_",
		"color":"white",
		"flags":[ "TRADER_AVOID","UNBREAKABLE_MELEE" ],
		"skill":"fabrication",
		"max_level":1,
		"intelligence":1,
		"time":20,
		"fun":1
	}
,
	{
		"id":"ncard_misc_ev5_event_box",
		"type":"TOOL",
		"category":"tools",
		"looks_like":"card_call_crate_1",
		"name":"신기한 오르골 상자",
		"description":"졸음을 유발하는 음색을 내는 오르골 상자입니다.좋은 게 들어있을 수도 있어요.사용하는 커맨드(a키)로 설치할 수 있습니다.",
		"weight":"30 g",
		"volume":"30 ml",
		"material":[ "ncard_material_dimensionsteel" ],
		"symbol":"n",
		"color":"yellow",
		"flags":[ "TRADER_AVOID","UNBREAKABLE_MELEE" ],
		"use_action":{ "type": "deploy_furn", "furn_type": "f_lootcrate_ev5_event_box" }
	}
,
	{
		"id":"ncard_misc_ev5_cushion",
		"type":"GENERIC",
		"copy-from":"bodypillow",
		"name":"푹신푹신한 쿠션(백색)",
		"description":"푹신푹신한 쿠션입니다.푹신푹신하게 자신을 맡기면 몸도 마음도 푹신푹신해지겠죠.",
		"material":[ "cotton" ],
		"color":"white",
		"flags":[ "TRADER_AVOID","UNBREAKABLE_MELEE","SLEEP_AID" ]
	}
,
	{
		"id":"ncard_misc_ev5_cushion2",
		"type":"GENERIC",
		"copy-from":"ncard_misc_ev5_cushion",
		"name":"푹신푹신한 쿠션(자주색)",
		"material":[ "cotton" ],
		"color":"magenta"
	}
,
	{
		"id":"ncard_misc_ev5_cushion3",
		"type":"GENERIC",
		"copy-from":"ncard_misc_ev5_cushion",
		"name":"푹신푹신한 쿠션(적색)",
		"material":[ "cotton" ],
		"color":"red"
	}
,
	{
		"id":"ncard_misc_ev5_cushion4",
		"type":"GENERIC",
		"copy-from":"ncard_misc_ev5_cushion",
		"name":"푹신푹신한 쿠션(주황색)",
		"material":[ "cotton" ],
		"color":"yellow"
	}
,
	{
		"id":"ncard_misc_ev5_cushion5",
		"type":"GENERIC",
		"copy-from":"ncard_misc_ev5_cushion",
		"name":"푹신푹신한 쿠션(녹색)",
		"material":[ "cotton" ],
		"color":"green"
	}
,
	{
		"id":"ncard_misc_ev5_cushion6",
		"type":"GENERIC",
		"copy-from":"ncard_misc_ev5_cushion",
		"name":"푹신푹신한 쿠션(물색)",
		"material":[ "cotton" ],
		"color":"light_cyan"
	}
,
	{
		"id":"ncard_misc_ev5_cushion7",
		"type":"GENERIC",
		"copy-from":"ncard_misc_ev5_cushion",
		"name":"푹신푹신한 쿠션(청색)",
		"material":[ "cotton" ],
		"color":"cyan"
	}
,
	{
		"id":"card_call_crate_ev6_1",
		"type":"TOOL",
		"looks_like":"card_call_crate_1",
		"name":"NEW YEAR가챠 티켓(묘)",
		"description":"기묘한 도안이나 문양이 그려진 티켓. 한 장 뜯어서 의사를 담으면 무슨 일이 일어날지도 모릅니다.반경 3미터 이내에 아무것도 없는 상태에서 사용하십시오.이를 만들려면 먼저 '십이지상극도(묘)'를 얻어야 합니다.",
		"weight":"1 g",
		"volume":"1 ml",
		"material":[ "paper" ],
		"symbol":"_",
		"color":"light_gray",
		"flags":[ "TRADER_AVOID","NO_UNLOAD","NO_RELOAD","UNBREAKABLE_MELEE" ],
		"pocket_data":[ { "pocket_type": "MAGAZINE",  "ammo_restriction": { "ncard_misc_t": 1 } } ],
		"use_action":{ "type": "cast_spell", "spell_id": "call_crate_ev6_", "no_fail": true, "level": 0 },
		"to_hit":-1,
		"initial_charges":1,
		"max_charges":1,
		"charges_per_use":1
	}
,
	{
		"id":"card_call_crate_ev6_2",
		"type":"TOOL",
		"looks_like":"card_call_crate_1",
		"name":"NEW YEAR가챠 티켓(묘)(10개 묶음)",
		"description":"기묘한 도안이나 문양이 그려진 티켓. 한 장 뜯어서 의사를 담으면 무슨 일이 일어날지도 모릅니다.반경 3미터 이내에 아무것도 없는 상태에서 사용하십시오.이를 만들려면 먼저 '십이지상극도(墓)'를 얻어야 합니다.",
		"weight":"1 g",
		"volume":"1 ml",
		"material":[ "paper" ],
		"symbol":"_",
		"color":"light_gray",
		"flags":[ "TRADER_AVOID","NO_UNLOAD","NO_RELOAD","UNBREAKABLE_MELEE" ],
		"pocket_data":[ { "pocket_type": "MAGAZINE",  "ammo_restriction": { "ncard_misc_t": 10 } } ],
		"use_action":{ "type": "cast_spell", "spell_id": "call_crate_ev6_", "no_fail": true, "level": 0 },
		"to_hit":-1,
		"initial_charges":10,
		"max_charges":10,
		"charges_per_use":1
	}
,
	{
		"id":"card_call_crate_ev6_3",
		"type":"TOOL",
		"looks_like":"card_call_crate_1",
		"name":"NEW YEAR가챠 티켓(묘)(100개 묶음)",
		"description":"기묘한 도안이나 문양이 그려진 티켓. 한 장 뜯어서 의사를 담으면 무슨 일이 일어날지도 모릅니다.반경 3미터 이내에 아무것도 없는 상태에서 사용하십시오.이를 만들려면 먼저 '십이지상극도(墓)'를 얻어야 합니다.",
		"weight":"1 g",
		"volume":"1 ml",
		"material":[ "paper" ],
		"symbol":"_",
		"color":"light_gray",
		"flags":[ "TRADER_AVOID","NO_UNLOAD","NO_RELOAD","UNBREAKABLE_MELEE" ],
		"pocket_data":[ { "pocket_type": "MAGAZINE",  "ammo_restriction": { "ncard_misc_t": 100 } } ],
		"use_action":{ "type": "cast_spell", "spell_id": "call_crate_ev6_", "no_fail": true, "level": 0 },
		"to_hit":-1,
		"initial_charges":100,
		"max_charges":100,
		"charges_per_use":1
	}
,
	{
		"id":"ncard_misc_ev6_keystone",
		"type":"BOOK",
		"looks_like":"ncard_misc_ev1_keystone",
		"name":"십이지상극도(묘)",
		"description":"이것을 읽는 것으로 NEW YEAR가챠 티켓(묘)을 만드는 방법을 알게됩니다.",
		"weight":"30 g",
		"volume":"30 ml",
		"material":[ "paper" ],
		"symbol":"_",
		"color":"white",
		"flags":[ "TRADER_AVOID","UNBREAKABLE_MELEE" ],
		"skill":"fabrication",
		"max_level":1,
		"intelligence":1,
		"time":20,
		"fun":1
	}
,
	{
		"id":"ncard_misc_ev6_event_box",
		"type":"TOOL",
		"category":"tools",
		"looks_like":"ncard_misc_ev2_event_box",
		"name":"복주머니",
		"description":"화려한 색상이 눈길을 끄는 빨간 종이봉투입니다.좋은 게 들어있을 수도 있어요.사용하는 커맨드(a키)로 설치할 수 있습니다.",
		"weight":"30 g",
		"volume":"30 ml",
		"material":[ "ncard_material_dimensionsteel" ],
		"symbol":"n",
		"color":"yellow",
		"flags":[ "TRADER_AVOID","UNBREAKABLE_MELEE" ],
		"use_action":{ "type": "deploy_furn", "furn_type": "f_lootcrate_ev6_event_box" }
	}


]
