[
  {
    "type": "TOOL",
    "id": "PSY_magi_stave_magic_druid_veggrasp_1",
    "name": { "str": "하급 지팡이(초목의 옭아매기)[MWMI]", "str_pl": "하급 지팡이(초목의 옭아매기)[MWMI]" },
    "copy-from": "staff_magic",
    "description": "마나 크리스탈을 끼우는 소켓이 달린 길쭉한 나무 지팡이입니다. 초목의 옭아매기을 영창하는 기능을 가지고 있습니다.",
    "price": "200 USD",
    "price_postapoc": "200 USD",
    "use_action": { "type": "cast_spell", "spell_id": "druid_veggrasp", "no_fail": true, "level": 4, "need_wielding": true }
  },
  {
    "type": "TOOL",
    "id": "PSY_magi_stave_magic_druid_veggrasp_2",
    "name": { "str": "중급 지팡이(초목의 옭아매기)[MWMI]", "str_pl": "중급 지팡이(초목의 옭아매기)[MWMI]" },
    "copy-from": "staff_magic",
    "description": "마나 크리스탈을 끼우는 소켓이 달린 길쭉한 나무 지팡이입니다. 초목의 옭아매기을 영창하는 기능을 가지고 있습니다.",
    "price": "400 USD",
    "price_postapoc": "400 USD",
    "use_action": { "type": "cast_spell", "spell_id": "druid_veggrasp", "no_fail": true, "level": 8, "need_wielding": true }
  },
  {
    "type": "TOOL",
    "id": "PSY_magi_stave_magic_druid_veggrasp_3",
    "name": { "str": "상급 지팡이(초목의 옭아매기)[MWMI]", "str_pl": "상급 지팡이(초목의 옭아매기)[MWMI]" },
    "copy-from": "staff_magic",
    "description": "마나 크리스탈을 끼우는 소켓이 달린 길쭉한 나무 지팡이입니다. 초목의 옭아매기을 영창하는 기능을 가지고 있습니다.",
    "price": "600 USD",
    "price_postapoc": "600 USD",
    "use_action": { "type": "cast_spell", "spell_id": "druid_veggrasp", "no_fail": true, "level": 12, "need_wielding": true }
  },
  {
    "type": "TOOL",
    "id": "PSY_magi_stave_magic_druid_rootstrike_1",
    "name": { "str": "하급 지팡이(뿌리 타격)[MWMI]", "str_pl": "하급 지팡이(뿌리 타격)[MWMI]" },
    "copy-from": "staff_magic",
    "description": "마나 크리스탈을 끼우는 소켓이 달린 길쭉한 나무 지팡이입니다. 뿌리 타격을 영창하는 기능을 가지고 있습니다.",
    "price": "200 USD",
    "price_postapoc": "200 USD",
    "use_action": { "type": "cast_spell", "spell_id": "druid_rootstrike", "no_fail": true, "level": 4, "need_wielding": true }
  },
  {
    "type": "TOOL",
    "id": "PSY_magi_stave_magic_druid_rootstrike_2",
    "name": { "str": "중급 지팡이(뿌리 타격)[MWMI]", "str_pl": "중급 지팡이(뿌리 타격)[MWMI]" },
    "copy-from": "staff_magic",
    "description": "마나 크리스탈을 끼우는 소켓이 달린 길쭉한 나무 지팡이입니다. 뿌리 타격을 영창하는 기능을 가지고 있습니다.",
    "price": "400 USD",
    "price_postapoc": "400 USD",
    "use_action": { "type": "cast_spell", "spell_id": "druid_rootstrike", "no_fail": true, "level": 8, "need_wielding": true }
  },
  {
    "type": "TOOL",
    "id": "PSY_magi_stave_magic_druid_rootstrike_3",
    "name": { "str": "상급 지팡이(뿌리 타격)[MWMI]", "str_pl": "상급 지팡이(뿌리 타격)[MWMI]" },
    "copy-from": "staff_magic",
    "description": "마나 크리스탈을 끼우는 소켓이 달린 길쭉한 나무 지팡이입니다. 뿌리 타격을 영창하는 기능을 가지고 있습니다.",
    "price": "600 USD",
    "price_postapoc": "600 USD",
    "use_action": { "type": "cast_spell", "spell_id": "druid_rootstrike", "no_fail": true, "level": 12, "need_wielding": true }
  },
  {
    "type": "TOOL",
    "id": "PSY_magi_stave_magic_summon_cats_1",
    "name": { "str": "하급 지팡이(백 오브 캣츠)[MWMI]", "str_pl": "하급 지팡이(백 오브 캣츠)[MWMI]" },
    "copy-from": "staff_magic",
    "description": "마나 크리스탈을 끼우는 소켓이 달린 길쭉한 나무 지팡이입니다. 백 오브 캣츠을 영창하는 기능을 가지고 있습니다.",
    "price": "200 USD",
    "price_postapoc": "200 USD",
    "use_action": { "type": "cast_spell", "spell_id": "summon_cats", "no_fail": true, "level": 4, "need_wielding": true }
  },
  {
    "type": "TOOL",
    "id": "PSY_magi_stave_magic_summon_cats_2",
    "name": { "str": "중급 지팡이(백 오브 캣츠)[MWMI]", "str_pl": "중급 지팡이(백 오브 캣츠)[MWMI]" },
    "copy-from": "staff_magic",
    "description": "마나 크리스탈을 끼우는 소켓이 달린 길쭉한 나무 지팡이입니다. 백 오브 캣츠을 영창하는 기능을 가지고 있습니다.",
    "price": "400 USD",
    "price_postapoc": "400 USD",
    "use_action": { "type": "cast_spell", "spell_id": "summon_cats", "no_fail": true, "level": 8, "need_wielding": true }
  },
  {
    "type": "TOOL",
    "id": "PSY_magi_stave_magic_summon_cats_3",
    "name": { "str": "상급 지팡이(백 오브 캣츠)[MWMI]", "str_pl": "상급 지팡이(백 오브 캣츠)[MWMI]" },
    "copy-from": "staff_magic",
    "description": "마나 크리스탈을 끼우는 소켓이 달린 길쭉한 나무 지팡이입니다. 백 오브 캣츠을 영창하는 기능을 가지고 있습니다.",
    "price": "600 USD",
    "price_postapoc": "600 USD",
    "use_action": { "type": "cast_spell", "spell_id": "summon_cats", "no_fail": true, "level": 12, "need_wielding": true }
  }
]
