[
	{
		"id":"card_call_crate_s2_1",
		"type":"TOOL",
		"looks_like":"card_call_crate_1",
		"name":"기계의 행진 가챠 티켓 ",
		"description":"기묘한 도안이나 문양이 그려진 티켓. 한 장 뜯어서 의사를 담으면  무슨 일이 생길지도 몰라요. 반경 3미터 이내에 아무것도 없는 상태로 사용해 주세요. 이것을 만들기 위해서는 먼저 '기계문명의 데이터 스톤' 을 만들어야 합니다.",
		"weight":"1 g",
		"volume":"1 ml",
		"material":[ "paper" ],
		"symbol":"_",
		"color":"light_gray",
		"flags":[ "TRADER_AVOID","NO_UNLOAD","NO_RELOAD","UNBREAKABLE_MELEE" ],
		"pocket_data":[ { "pocket_type": "MAGAZINE",  "ammo_restriction": { "ncard_misc_t": 1 } } ],
		"use_action":{ "type": "cast_spell", "spell_id": "call_crate_s2_", "no_fail": true, "level": 0 },
		"to_hit":-1,
		"initial_charges":1,
		"max_charges":1,
		"charges_per_use":1
	}
,
	{
		"id":"card_call_crate_s2_2",
		"type":"TOOL",
		"looks_like":"card_call_crate_1",
		"name":"기계의 행진 가챠 티켓 (10개 묶음)",
		"description":"기묘한 도안이나 문양이 그려진 티켓. 한 장 뜯어서 의사를 담으면  무슨 일이 생길지도 몰라요. 반경 3미터 이내에 아무것도 없는 상태로 사용해 주세요. 이것을 만들기 위해서는 먼저 '기계문명의 데이터 스톤' 을 만들어야 합니다.",
		"weight":"1 g",
		"volume":"1 ml",
		"material":[ "paper" ],
		"symbol":"_",
		"color":"light_gray",
		"flags":[ "TRADER_AVOID","NO_UNLOAD","NO_RELOAD","UNBREAKABLE_MELEE" ],
		"pocket_data":[ { "pocket_type": "MAGAZINE",  "ammo_restriction": { "ncard_misc_t": 10 } } ],
		"use_action":{ "type": "cast_spell", "spell_id": "call_crate_s2_", "no_fail": true, "level": 0 },
		"to_hit":-1,
		"initial_charges":10,
		"max_charges":10,
		"charges_per_use":1
	}
,
	{
		"id":"card_call_crate_s2_3",
		"type":"TOOL",
		"looks_like":"card_call_crate_1",
		"name":"기계의 행진 가챠 티켓 (100개 묶음)",
		"description":"기묘한 도안이나 문양이 그려진 티켓. 한 장 뜯어서 의사를 담으면  무슨 일이 생길지도 몰라요. 반경 3미터 이내에 아무것도 없는 상태로 사용해 주세요. 이것을 만들기 위해서는 먼저 '기계문명의 데이터 스톤' 을 만들어야 합니다.",
		"weight":"1 g",
		"volume":"1 ml",
		"material":[ "paper" ],
		"symbol":"_",
		"color":"light_gray",
		"flags":[ "TRADER_AVOID","NO_UNLOAD","NO_RELOAD","UNBREAKABLE_MELEE" ],
		"pocket_data":[ { "pocket_type": "MAGAZINE",  "ammo_restriction": { "ncard_misc_t": 100 } } ],
		"use_action":{ "type": "cast_spell", "spell_id": "call_crate_s2_", "no_fail": true, "level": 0 },
		"to_hit":-1,
		"initial_charges":100,
		"max_charges":100,
		"charges_per_use":1
	}
,
	{
		"id":"ncard_misc_s2_keystone",
		"type":"BOOK",
		"copy-from":"spiral_stone",
		"name":"기계문명의 데이터 스톤",
		"description":"기계문명의 기술 및 정보가 담긴 구체입니다.이것을 손에 넣음으로써 '기계의 행진 가챠 티켓' 를 제작할 수 있습니다.",
		"weight":"30 kg",
		"volume":"30 L",
		"material":[ "ncard_material_dimensionsteel" ],
		"symbol":"O",
		"color":"light_cyan",
		"flags":[ "TRADER_AVOID","UNBREAKABLE_MELEE" ],
		"skill":"fabrication",
		"max_level":10,
		"intelligence":14,
		"time":20,
		"fun":-1
	}
,
	{
		"id":"ncard_misc_s2_keystone_1",
		"type":"BOOK",
		"copy-from":"spiral_stone",
		"name":"기계문명의 데이터 스톤(상부)",
		"description":"기계문명의 기술이나 정보가 담긴 구체의 절반입니다.다른 한 쪽과 결합하면 완전한 기능을 되찾습니다.이것을 자세히 확인하는 것으로 조립 방법을 알 수 있을 것입니다.",
		"weight":"15 kg",
		"volume":"15 L",
		"material":[ "ncard_material_dimensionsteel" ],
		"symbol":"*",
		"color":"light_cyan",
		"flags":[ "TRADER_AVOID","UNBREAKABLE_MELEE" ],
		"skill":"fabrication",
		"max_level":10,
		"intelligence":14,
		"time":120,
		"fun":-1
	}
,
	{
		"id":"ncard_misc_s2_keystone_2",
		"type":"BOOK",
		"copy-from":"spiral_stone",
		"name":"기계문명의 데이터 스톤(하부)",
		"description":"기계문명의 기술이나 정보가 담긴 구체의 절반입니다.다른 한 쪽과 결합하면 완전한 기능을 되찾습니다.이것을 자세히 확인하는 것으로 조립 방법을 알 수 있을 것입니다.",
		"weight":"15 kg",
		"volume":"15 L",
		"material":[ "ncard_material_dimensionsteel" ],
		"symbol":"*",
		"color":"light_cyan",
		"flags":[ "TRADER_AVOID","UNBREAKABLE_MELEE" ],
		"skill":"fabrication",
		"max_level":10,
		"intelligence":14,
		"time":120,
		"fun":-1
	}


]
